<?xml version="1.0" encoding="UTF-8"?>
<Doc>
	<Invoices>
		<Invoice>
			<Vendor ID="6009510800005">THE SIMBA GROUP</Vendor>
			<InvoiceNo>IN02099975</InvoiceNo>
			<OrderNo>0000000039465</OrderNo>
			<Depot ID="0">THE SIMBA GROUP</Depot>
			<InvoiceDate>25/05/2023</InvoiceDate>
			<OrderDate>25/05/2023</OrderDate>
			<DropDate></DropDate>
			<OrderCode>N</OrderCode>
			<Buyer/>
			<Dept/>
			<SubDept/>
			<InvoiceDetails>
				<Destins>
					<Destin>
						<DestID>40349</DestID>
						<DestDesc>KWA FETTING SPAR</DestDesc>
						<DestEAN></DestEAN>
						<Items>
							<Item>
								<ItemNum>1</ItemNum>
								<Qty>6</Qty>
								<ContractNo/>
								<CostPer>148.5</CostPer>
								<CostUnitMeasure/>
								<GrossCst>891.00</GrossCst>
								<Vat>15</Vat>
								<ExtendCst/>
								<FreeStock></FreeStock>
								<FreeOrdBase></FreeOrdBase>
								<FreeOrdQty>0</FreeOrdQty>
								<DelInstr1/>
								<DelInstr2/>
								<ExpDelDate/>
								<Discounts>
									<Discount>
										<Indicator1>T1</Indicator1>
										<Percentage1>0</Percentage1>
										<Value1>0</Value1>
										<Indicator2>T2</Indicator2>
										<Percentage2>0</Percentage2>
										<Value2>0</Value2>
									</Discount>
								</Discounts>
							</Item>
							<Item>
								<ItemNum>2</ItemNum>
								<Qty>2</Qty>
								<ContractNo/>
								<CostPer>229.5</CostPer>
								<CostUnitMeasure/>
								<GrossCst>459.00</GrossCst>
								<Vat>15</Vat>
								<ExtendCst/>
								<FreeStock></FreeStock>
								<FreeOrdBase></FreeOrdBase>
								<FreeOrdQty>0</FreeOrdQty>
								<DelInstr1/>
								<DelInstr2/>
								<ExpDelDate/>
								<Discounts>
									<Discount>
										<Indicator1>T1</Indicator1>
										<Percentage1>0</Percentage1>
										<Value1>0</Value1>
										<Indicator2>T2</Indicator2>
										<Percentage2>0</Percentage2>
										<Value2>0</Value2>
									</Discount>
								</Discounts>
							</Item>
							<Item>
								<ItemNum>3</ItemNum>
								<Qty>1</Qty>
								<ContractNo/>
								<CostPer>207.5</CostPer>
								<CostUnitMeasure/>
								<GrossCst>207.50</GrossCst>
								<Vat>15</Vat>
								<ExtendCst/>
								<FreeStock></FreeStock>
								<FreeOrdBase></FreeOrdBase>
								<FreeOrdQty>0</FreeOrdQty>
								<DelInstr1/>
								<DelInstr2/>
								<ExpDelDate/>
								<Discounts>
									<Discount>
										<Indicator1>T1</Indicator1>
										<Percentage1>0</Percentage1>
										<Value1>0</Value1>
										<Indicator2>T2</Indicator2>
										<Percentage2>0</Percentage2>
										<Value2>0</Value2>
									</Discount>
								</Discounts>
							</Item>
							<Item>
								<ItemNum>4</ItemNum>
								<Qty>1</Qty>
								<ContractNo/>
								<CostPer>207.5</CostPer>
								<CostUnitMeasure/>
								<GrossCst>207.50</GrossCst>
								<Vat>15</Vat>
								<ExtendCst/>
								<FreeStock></FreeStock>
								<FreeOrdBase></FreeOrdBase>
								<FreeOrdQty>0</FreeOrdQty>
								<DelInstr1/>
								<DelInstr2/>
								<ExpDelDate/>
								<Discounts>
									<Discount>
										<Indicator1>T1</Indicator1>
										<Percentage1>0</Percentage1>
										<Value1>0</Value1>
										<Indicator2>T2</Indicator2>
										<Percentage2>0</Percentage2>
										<Value2>0</Value2>
									</Discount>
								</Discounts>
							</Item>
							<Item>
								<ItemNum>5</ItemNum>
								<Qty>1</Qty>
								<ContractNo/>
								<CostPer>151</CostPer>
								<CostUnitMeasure/>
								<GrossCst>151.00</GrossCst>
								<Vat>15</Vat>
								<ExtendCst/>
								<FreeStock></FreeStock>
								<FreeOrdBase></FreeOrdBase>
								<FreeOrdQty>0</FreeOrdQty>
								<DelInstr1/>
								<DelInstr2/>
								<ExpDelDate/>
								<Discounts>
									<Discount>
										<Indicator1>T1</Indicator1>
										<Percentage1>0</Percentage1>
										<Value1>0</Value1>
										<Indicator2>T2</Indicator2>
										<Percentage2>0</Percentage2>
										<Value2>0</Value2>
									</Discount>
								</Discounts>
							</Item>
							<Item>
								<ItemNum>6</ItemNum>
								<Qty>1</Qty>
								<ContractNo/>
								<CostPer>151</CostPer>
								<CostUnitMeasure/>
								<GrossCst>151.00</GrossCst>
								<Vat>15</Vat>
								<ExtendCst/>
								<FreeStock></FreeStock>
								<FreeOrdBase></FreeOrdBase>
								<FreeOrdQty>0</FreeOrdQty>
								<DelInstr1/>
								<DelInstr2/>
								<ExpDelDate/>
								<Discounts>
									<Discount>
										<Indicator1>T1</Indicator1>
										<Percentage1>0</Percentage1>
										<Value1>0</Value1>
										<Indicator2>T2</Indicator2>
										<Percentage2>0</Percentage2>
										<Value2>0</Value2>
									</Discount>
								</Discounts>
							</Item>
							<Item>
								<ItemNum>7</ItemNum>
								<Qty>1</Qty>
								<ContractNo/>
								<CostPer>236</CostPer>
								<CostUnitMeasure/>
								<GrossCst>236.00</GrossCst>
								<Vat>15</Vat>
								<ExtendCst/>
								<FreeStock></FreeStock>
								<FreeOrdBase></FreeOrdBase>
								<FreeOrdQty>0</FreeOrdQty>
								<DelInstr1/>
								<DelInstr2/>
								<ExpDelDate/>
								<Discounts>
									<Discount>
										<Indicator1>T1</Indicator1>
										<Percentage1>0</Percentage1>
										<Value1>0</Value1>
										<Indicator2>T2</Indicator2>
										<Percentage2>0</Percentage2>
										<Value2>0</Value2>
									</Discount>
								</Discounts>
							</Item>
							<Item>
								<ItemNum>8</ItemNum>
								<Qty>3</Qty>
								<ContractNo/>
								<CostPer>309.5</CostPer>
								<CostUnitMeasure/>
								<GrossCst>913.50</GrossCst>
								<Vat>15</Vat>
								<ExtendCst/>
								<FreeStock></FreeStock>
								<FreeOrdBase></FreeOrdBase>
								<FreeOrdQty>0</FreeOrdQty>
								<DelInstr1/>
								<DelInstr2/>
								<ExpDelDate/>
								<Discounts>
									<Discount>
										<Indicator1>T1</Indicator1>
										<Percentage1>1.62</Percentage1>
										<Value1>15</Value1>
										<Indicator2>T2</Indicator2>
										<Percentage2>0</Percentage2>
										<Value2>0</Value2>
									</Discount>
								</Discounts>
							</Item>
							<Item>
								<ItemNum>9</ItemNum>
								<Qty>1</Qty>
								<ContractNo/>
								<CostPer>309.5</CostPer>
								<CostUnitMeasure/>
								<GrossCst>304.50</GrossCst>
								<Vat>15</Vat>
								<ExtendCst/>
								<FreeStock></FreeStock>
								<FreeOrdBase></FreeOrdBase>
								<FreeOrdQty>0</FreeOrdQty>
								<DelInstr1/>
								<DelInstr2/>
								<ExpDelDate/>
								<Discounts>
									<Discount>
										<Indicator1>T1</Indicator1>
										<Percentage1>1.62</Percentage1>
										<Value1>5</Value1>
										<Indicator2>T2</Indicator2>
										<Percentage2>0</Percentage2>
										<Value2>0</Value2>
									</Discount>
								</Discounts>
							</Item>
							<Item>
								<ItemNum>10</ItemNum>
								<Qty>1</Qty>
								<ContractNo/>
								<CostPer>321</CostPer>
								<CostUnitMeasure/>
								<GrossCst>309.00</GrossCst>
								<Vat>15</Vat>
								<ExtendCst/>
								<FreeStock></FreeStock>
								<FreeOrdBase></FreeOrdBase>
								<FreeOrdQty>0</FreeOrdQty>
								<DelInstr1/>
								<DelInstr2/>
								<ExpDelDate/>
								<Discounts>
									<Discount>
										<Indicator1>T1</Indicator1>
										<Percentage1>3.74</Percentage1>
										<Value1>12</Value1>
										<Indicator2>T2</Indicator2>
										<Percentage2>0</Percentage2>
										<Value2>0</Value2>
									</Discount>
								</Discounts>
							</Item>
							<Item>
								<ItemNum>11</ItemNum>
								<Qty>1</Qty>
								<ContractNo/>
								<CostPer>123</CostPer>
								<CostUnitMeasure/>
								<GrossCst>123.00</GrossCst>
								<Vat>15</Vat>
								<ExtendCst/>
								<FreeStock></FreeStock>
								<FreeOrdBase></FreeOrdBase>
								<FreeOrdQty>0</FreeOrdQty>
								<DelInstr1/>
								<DelInstr2/>
								<ExpDelDate/>
								<Discounts>
									<Discount>
										<Indicator1>T1</Indicator1>
										<Percentage1>0</Percentage1>
										<Value1>0</Value1>
										<Indicator2>T2</Indicator2>
										<Percentage2>0</Percentage2>
										<Value2>0</Value2>
									</Discount>
								</Discounts>
							</Item>
							<Item>
								<ItemNum>12</ItemNum>
								<Qty>1</Qty>
								<ContractNo/>
								<CostPer>236</CostPer>
								<CostUnitMeasure/>
								<GrossCst>236.00</GrossCst>
								<Vat>15</Vat>
								<ExtendCst/>
								<FreeStock></FreeStock>
								<FreeOrdBase></FreeOrdBase>
								<FreeOrdQty>0</FreeOrdQty>
								<DelInstr1/>
								<DelInstr2/>
								<ExpDelDate/>
								<Discounts>
									<Discount>
										<Indicator1>T1</Indicator1>
										<Percentage1>0</Percentage1>
										<Value1>0</Value1>
										<Indicator2>T2</Indicator2>
										<Percentage2>0</Percentage2>
										<Value2>0</Value2>
									</Discount>
								</Discounts>
							</Item>
							<Item>
								<ItemNum>13</ItemNum>
								<Qty>1</Qty>
								<ContractNo/>
								<CostPer>236</CostPer>
								<CostUnitMeasure/>
								<GrossCst>236.00</GrossCst>
								<Vat>15</Vat>
								<ExtendCst/>
								<FreeStock></FreeStock>
								<FreeOrdBase></FreeOrdBase>
								<FreeOrdQty>0</FreeOrdQty>
								<DelInstr1/>
								<DelInstr2/>
								<ExpDelDate/>
								<Discounts>
									<Discount>
										<Indicator1>T1</Indicator1>
										<Percentage1>0</Percentage1>
										<Value1>0</Value1>
										<Indicator2>T2</Indicator2>
										<Percentage2>0</Percentage2>
										<Value2>0</Value2>
									</Discount>
								</Discounts>
							</Item>
							<Item>
								<ItemNum>14</ItemNum>
								<Qty>1</Qty>
								<ContractNo/>
								<CostPer>215.5</CostPer>
								<CostUnitMeasure/>
								<GrossCst>215.50</GrossCst>
								<Vat>15</Vat>
								<ExtendCst/>
								<FreeStock></FreeStock>
								<FreeOrdBase></FreeOrdBase>
								<FreeOrdQty>0</FreeOrdQty>
								<DelInstr1/>
								<DelInstr2/>
								<ExpDelDate/>
								<Discounts>
									<Discount>
										<Indicator1>T1</Indicator1>
										<Percentage1>0</Percentage1>
										<Value1>0</Value1>
										<Indicator2>T2</Indicator2>
										<Percentage2>0</Percentage2>
										<Value2>0</Value2>
									</Discount>
								</Discounts>
							</Item>
							<Item>
								<ItemNum>15</ItemNum>
								<Qty>3</Qty>
								<ContractNo/>
								<CostPer>321</CostPer>
								<CostUnitMeasure/>
								<GrossCst>927.00</GrossCst>
								<Vat>15</Vat>
								<ExtendCst/>
								<FreeStock></FreeStock>
								<FreeOrdBase></FreeOrdBase>
								<FreeOrdQty>0</FreeOrdQty>
								<DelInstr1/>
								<DelInstr2/>
								<ExpDelDate/>
								<Discounts>
									<Discount>
										<Indicator1>T1</Indicator1>
										<Percentage1>3.74</Percentage1>
										<Value1>36</Value1>
										<Indicator2>T2</Indicator2>
										<Percentage2>0</Percentage2>
										<Value2>0</Value2>
									</Discount>
								</Discounts>
							</Item>
							<Item>
								<ItemNum>16</ItemNum>
								<Qty>2</Qty>
								<ContractNo/>
								<CostPer>321</CostPer>
								<CostUnitMeasure/>
								<GrossCst>618.00</GrossCst>
								<Vat>15</Vat>
								<ExtendCst/>
								<FreeStock></FreeStock>
								<FreeOrdBase></FreeOrdBase>
								<FreeOrdQty>0</FreeOrdQty>
								<DelInstr1/>
								<DelInstr2/>
								<ExpDelDate/>
								<Discounts>
									<Discount>
										<Indicator1>T1</Indicator1>
										<Percentage1>3.74</Percentage1>
										<Value1>24</Value1>
										<Indicator2>T2</Indicator2>
										<Percentage2>0</Percentage2>
										<Value2>0</Value2>
									</Discount>
								</Discounts>
							</Item>
							<Item>
								<ItemNum>17</ItemNum>
								<Qty>2</Qty>
								<ContractNo/>
								<CostPer>321</CostPer>
								<CostUnitMeasure/>
								<GrossCst>618.00</GrossCst>
								<Vat>15</Vat>
								<ExtendCst/>
								<FreeStock></FreeStock>
								<FreeOrdBase></FreeOrdBase>
								<FreeOrdQty>0</FreeOrdQty>
								<DelInstr1/>
								<DelInstr2/>
								<ExpDelDate/>
								<Discounts>
									<Discount>
										<Indicator1>T1</Indicator1>
										<Percentage1>3.74</Percentage1>
										<Value1>24</Value1>
										<Indicator2>T2</Indicator2>
										<Percentage2>0</Percentage2>
										<Value2>0</Value2>
									</Discount>
								</Discounts>
							</Item>
							<Item>
								<ItemNum>18</ItemNum>
								<Qty>1</Qty>
								<ContractNo/>
								<CostPer>309.5</CostPer>
								<CostUnitMeasure/>
								<GrossCst>309.50</GrossCst>
								<Vat>15</Vat>
								<ExtendCst/>
								<FreeStock></FreeStock>
								<FreeOrdBase></FreeOrdBase>
								<FreeOrdQty>0</FreeOrdQty>
								<DelInstr1/>
								<DelInstr2/>
								<ExpDelDate/>
								<Discounts>
									<Discount>
										<Indicator1>T1</Indicator1>
										<Percentage1>0</Percentage1>
										<Value1>0</Value1>
										<Indicator2>T2</Indicator2>
										<Percentage2>0</Percentage2>
										<Value2>0</Value2>
									</Discount>
								</Discounts>
							</Item>
							<Item>
								<ItemNum>19</ItemNum>
								<Qty>2</Qty>
								<ContractNo/>
								<CostPer>309.5</CostPer>
								<CostUnitMeasure/>
								<GrossCst>619.00</GrossCst>
								<Vat>15</Vat>
								<ExtendCst/>
								<FreeStock></FreeStock>
								<FreeOrdBase></FreeOrdBase>
								<FreeOrdQty>0</FreeOrdQty>
								<DelInstr1/>
								<DelInstr2/>
								<ExpDelDate/>
								<Discounts>
									<Discount>
										<Indicator1>T1</Indicator1>
										<Percentage1>0</Percentage1>
										<Value1>0</Value1>
										<Indicator2>T2</Indicator2>
										<Percentage2>0</Percentage2>
										<Value2>0</Value2>
									</Discount>
								</Discounts>
							</Item>
						</Items>
					</Destin>
				</Destins>
			</InvoiceDetails>
		</Invoice>
	</Invoices>
	<Products>
		<Prod>
			<ProdItemNo>1</ProdItemNo>
			<Barcode>16009510802938</Barcode>
			<SuppItemNo>003603</SuppItemNo>
			<ItemDesc>SIMB PN RS SALTED 36X50G</ItemDesc>
			<ItemPackSize>36</ItemPackSize>
			<WHOrderInd/>
		</Prod>
		<Prod>
			<ProdItemNo>2</ProdItemNo>
			<Barcode>16009510803485</Barcode>
			<SuppItemNo>005425</SuppItemNo>
			<ItemDesc>NIKN CHEESE 25X5X22G</ItemDesc>
			<ItemPackSize>25</ItemPackSize>
			<WHOrderInd/>
		</Prod>
		<Prod>
			<ProdItemNo>3</ProdItemNo>
			<Barcode>16009510804345</Barcode>
			<SuppItemNo>004993</SuppItemNo>
			<ItemDesc>SIMB MEXICA 48X36G</ItemDesc>
			<ItemPackSize>48</ItemPackSize>
			<WHOrderInd/>
		</Prod>
		<Prod>
			<ProdItemNo>4</ProdItemNo>
			<Barcode>16009510804376</Barcode>
			<SuppItemNo>004996</SuppItemNo>
			<ItemDesc>SIMB SMOKED 48X36G</ItemDesc>
			<ItemPackSize>48</ItemPackSize>
			<WHOrderInd/>
		</Prod>
		<Prod>
			<ProdItemNo>5</ProdItemNo>
			<Barcode>16009510805960</Barcode>
			<SuppItemNo>003607</SuppItemNo>
			<ItemDesc>SIMB PN SALTED 24X60G</ItemDesc>
			<ItemPackSize>24</ItemPackSize>
			<WHOrderInd/>
		</Prod>
		<Prod>
			<ProdItemNo>6</ProdItemNo>
			<Barcode>16009510805977</Barcode>
			<SuppItemNo>003608</SuppItemNo>
			<ItemDesc>SIMB PN RS SALTED 24X60G</ItemDesc>
			<ItemPackSize>24</ItemPackSize>
			<WHOrderInd/>
		</Prod>
		<Prod>
			<ProdItemNo>7</ProdItemNo>
			<Barcode>16009710723033</Barcode>
			<SuppItemNo>152645</SuppItemNo>
			<ItemDesc>LAYS SPICY SALSA 48X36G</ItemDesc>
			<ItemPackSize>48</ItemPackSize>
			<WHOrderInd/>
		</Prod>
		<Prod>
			<ProdItemNo>8</ProdItemNo>
			<Barcode>16009710721527</Barcode>
			<SuppItemNo>146175</SuppItemNo>
			<ItemDesc>DORITOS SWEET CHILLI 145G</ItemDesc>
			<ItemPackSize>20</ItemPackSize>
			<WHOrderInd/>
		</Prod>
		<Prod>
			<ProdItemNo>9</ProdItemNo>
			<Barcode>16009710721534</Barcode>
			<SuppItemNo>146176</SuppItemNo>
			<ItemDesc>DORITOS SUPREME CHEESE 145G</ItemDesc>
			<ItemPackSize>20</ItemPackSize>
			<WHOrderInd/>
		</Prod>
		<Prod>
			<ProdItemNo>10</ProdItemNo>
			<Barcode>16009710721787</Barcode>
			<SuppItemNo>148976</SuppItemNo>
			<ItemDesc>SIMBA HOTWINGS 24X120G</ItemDesc>
			<ItemPackSize>24</ItemPackSize>
			<WHOrderInd/>
		</Prod>
		<Prod>
			<ProdItemNo>11</ProdItemNo>
			<Barcode>16009710722401</Barcode>
			<SuppItemNo>148857</SuppItemNo>
			<ItemDesc>SIMBA MUNCHIEZ CHEESE 110G BAG</ItemDesc>
			<ItemPackSize>14</ItemPackSize>
			<WHOrderInd/>
		</Prod>
		<Prod>
			<ProdItemNo>12</ProdItemNo>
			<Barcode>16009710722432</Barcode>
			<SuppItemNo>150677</SuppItemNo>
			<ItemDesc>DORITOS 45G FLAMN HOT MASALA</ItemDesc>
			<ItemPackSize>48</ItemPackSize>
			<WHOrderInd/>
		</Prod>
		<Prod>
			<ProdItemNo>13</ProdItemNo>
			<Barcode>16009710723026</Barcode>
			<SuppItemNo>152644</SuppItemNo>
			<ItemDesc>LAYS YAKITORI CHICKEN 36G</ItemDesc>
			<ItemPackSize>48</ItemPackSize>
			<WHOrderInd/>
		</Prod>
		<Prod>
			<ProdItemNo>14</ProdItemNo>
			<Barcode>16009510808640</Barcode>
			<SuppItemNo>135996</SuppItemNo>
			<ItemDesc>NIKN CHEESE 22X135G</ItemDesc>
			<ItemPackSize>22</ItemPackSize>
			<WHOrderInd/>
		</Prod>
		<Prod>
			<ProdItemNo>15</ProdItemNo>
			<Barcode>16009510809456</Barcode>
			<SuppItemNo>140351</SuppItemNo>
			<ItemDesc>SIMBA CREAMY CHD 120G</ItemDesc>
			<ItemPackSize>24</ItemPackSize>
			<WHOrderInd/>
		</Prod>
		<Prod>
			<ProdItemNo>16</ProdItemNo>
			<Barcode>16009510809463</Barcode>
			<SuppItemNo>140349</SuppItemNo>
			<ItemDesc>SIMBA SMOKED BEEF 120G</ItemDesc>
			<ItemPackSize>24</ItemPackSize>
			<WHOrderInd/>
		</Prod>
		<Prod>
			<ProdItemNo>17</ProdItemNo>
			<Barcode>16009510809494</Barcode>
			<SuppItemNo>140366</SuppItemNo>
			<ItemDesc>SIMBA CHEESE  ONI 120G</ItemDesc>
			<ItemPackSize>24</ItemPackSize>
			<WHOrderInd/>
		</Prod>
		<Prod>
			<ProdItemNo>18</ProdItemNo>
			<Barcode>16009710720629</Barcode>
			<SuppItemNo>141505</SuppItemNo>
			<ItemDesc>LAYS SALTED 120G</ItemDesc>
			<ItemPackSize>20</ItemPackSize>
			<WHOrderInd/>
		</Prod>
		<Prod>
			<ProdItemNo>19</ProdItemNo>
			<Barcode>16009710720650</Barcode>
			<SuppItemNo>141520</SuppItemNo>
			<ItemDesc>LAYS SWT  SMK AMERICAN BBQ 12</ItemDesc>
			<ItemPackSize>20</ItemPackSize>
			<WHOrderInd/>
		</Prod>
	</Products>
	<PastOrders/>
</Doc>
